katapult_api/__init__.py
katapult_api/client.py
katapult_api/enums.py
katapult_api/katapult.py
katapult_api/katapult_nice.py
katapult_api/utils.py
katapult_api/structs/__init__.py
katapult_api/structs/response.py
katapult_api-1.2.1.dist-info/licenses/LICENSE
katapult_api-1.2.1.dist-info/METADATA
katapult_api-1.2.1.dist-info/WHEEL
katapult_api-1.2.1.dist-info/top_level.txt
katapult_api-1.2.1.dist-info/RECORD
