Metadata-Version: 2.4
Name: katapult-api
Version: 1.2.1
Summary: Async Python client for interacting with the KatapultPro API.
Author-email: TechServ Engineering Team <engineering@techserv.com>
License: MIT License
Requires-Python: >=3.12
License-File: LICENSE
Requires-Dist: aiohttp<4.0,>=3.11
Dynamic: license-file
